odoo/addons/__init__.py
odoo/addons/website_slides/__init__.py
odoo/addons/website_slides/__manifest__.py
odoo/addons/website_slides/controllers/__init__.py
odoo/addons/website_slides/controllers/main.py
odoo/addons/website_slides/data/website_slides_data.xml
odoo/addons/website_slides/data/website_slides_demo.xml
odoo/addons/website_slides/data/demo-thumbnails/8DBabYQ1nUE.jpg
odoo/addons/website_slides/data/demo-thumbnails/QtIU0p8daAo.jpg
odoo/addons/website_slides/data/demo-thumbnails/VMuCr5_arsY.jpg
odoo/addons/website_slides/data/demo-thumbnails/Vp5xqQOWLzE.jpg
odoo/addons/website_slides/data/demo-thumbnails/fgdz8MH2YHY.jpg
odoo/addons/website_slides/data/demo-thumbnails/sDxfUTd-gs0.jpg
odoo/addons/website_slides/data/demo-thumbnails/tUx39vAENy0.jpg
odoo/addons/website_slides/data/demo-thumbnails/v2O0YZU19ms.jpg
odoo/addons/website_slides/i18n/af.po
odoo/addons/website_slides/i18n/am.po
odoo/addons/website_slides/i18n/ar.po
odoo/addons/website_slides/i18n/bg.po
odoo/addons/website_slides/i18n/bs.po
odoo/addons/website_slides/i18n/ca.po
odoo/addons/website_slides/i18n/cs.po
odoo/addons/website_slides/i18n/da.po
odoo/addons/website_slides/i18n/de.po
odoo/addons/website_slides/i18n/el.po
odoo/addons/website_slides/i18n/en_GB.po
odoo/addons/website_slides/i18n/es.po
odoo/addons/website_slides/i18n/es_CL.po
odoo/addons/website_slides/i18n/es_CO.po
odoo/addons/website_slides/i18n/es_CR.po
odoo/addons/website_slides/i18n/es_DO.po
odoo/addons/website_slides/i18n/es_EC.po
odoo/addons/website_slides/i18n/es_PE.po
odoo/addons/website_slides/i18n/es_PY.po
odoo/addons/website_slides/i18n/es_VE.po
odoo/addons/website_slides/i18n/et.po
odoo/addons/website_slides/i18n/eu.po
odoo/addons/website_slides/i18n/fa.po
odoo/addons/website_slides/i18n/fi.po
odoo/addons/website_slides/i18n/fo.po
odoo/addons/website_slides/i18n/fr.po
odoo/addons/website_slides/i18n/gl.po
odoo/addons/website_slides/i18n/gu.po
odoo/addons/website_slides/i18n/he.po
odoo/addons/website_slides/i18n/hr.po
odooku_odoo_website_slides-11.0.7.dist-info/LICENSE
odooku_odoo_website_slides-11.0.7.dist-info/METADATA
odooku_odoo_website_slides-11.0.7.dist-info/WHEEL
odooku_odoo_website_slides-11.0.7.dist-info/top_level.txt
odooku_odoo_website_slides-11.0.7.dist-info/RECORD
